psycopg2_logical_decoding_json_consumer/__init__.py
psycopg2_logical_decoding_json_consumer-2.6.1.dist-info/LICENSE
psycopg2_logical_decoding_json_consumer-2.6.1.dist-info/METADATA
psycopg2_logical_decoding_json_consumer-2.6.1.dist-info/WHEEL
psycopg2_logical_decoding_json_consumer-2.6.1.dist-info/top_level.txt
psycopg2_logical_decoding_json_consumer-2.6.1.dist-info/RECORD
