Metadata-Version: 2.1
Name: psycopg2-logical-decoding-json-consumer
Version: 2.6.1
Summary: Asynchronous PostgreSQL logical replication consumer library for the logical-decoding-json logical decoding output plugin
Author: Graham Clinch
Author-email: g.clinch@lancaster.ac.uk
Classifier: Development Status :: 5 - Production/Stable
Classifier: License :: OSI Approved :: Apache Software License
Classifier: Topic :: Database
License-File: LICENSE
Requires-Dist: psycopg2 (>=2.8.4)
